twlib-2.3.0.dist-info/METADATA
twlib-2.3.0.dist-info/WHEEL
twlib-2.3.0.dist-info/entry_points.txt
twlib-2.3.0.dist-info/licenses/LICENSE
twlib/__init__.py
twlib/__main__.py
twlib/annotated.py
twlib/bin/__init__.py
twlib/bin/git_open.py
twlib/bin/main.py
twlib/bin/tokenize_vimwiki.py
twlib/environment.py
twlib/lib/__init__.py
twlib/lib/aws/__init__.py
twlib/lib/aws/ddb_correction_layer.py
twlib/lib/aws/metrics.py
twlib/lib/aws/sqs.py
twlib/lib/collection.py
twlib/lib/datetime/__init__.py
twlib/lib/datetime/datetime.py
twlib/lib/datetime/timer.py
twlib/lib/db/read_sql_file.py
twlib/lib/db/uri.py
twlib/lib/decorator/annotation.py
twlib/lib/dev/dynamic_loader.py
twlib/lib/dev/serialize_obj.py
twlib/lib/fun.py
twlib/lib/network.py
twlib/lib/osdir/__init__.py
twlib/lib/osdir/path.py
twlib/lib/string/__init__.py
twlib/lib/string/chunking.py
twlib/lib/string/escape_delimiter.py
twlib/lib/string/randstr.py
twlib-2.3.0.dist-info/RECORD
