Metadata-Version: 2.1
Name: twlib
Version: 2.3.0
Author-Email: sysid <sysid@gmx.de>
License: MIT
Classifier: Development Status :: 4 - Beta
Classifier: Intended Audience :: Developers
Classifier: License :: OSI Approved :: BSD License
Classifier: Operating System :: OS Independent
Classifier: Programming Language :: Python :: 3
Classifier: Programming Language :: Python :: 3.12
Requires-Python: >=3.11
Requires-Dist: typer
Requires-Dist: appdirs
Requires-Dist: pydantic
Requires-Dist: python-dateutil
Requires-Dist: pytz
Requires-Dist: pillow
Requires-Dist: pillow-heif
Requires-Dist: boto3
Requires-Dist: alembic
Requires-Dist: psycopg2-binary
Requires-Dist: sqlalchemy
Requires-Dist: pydantic-settings>=2.1.0
Requires-Dist: matplotlib>=3.8.2
Requires-Dist: bs4>=0.0.1
Requires-Dist: english-dictionary>=1.0.24
Requires-Dist: markdown>=3.5.1
Requires-Dist: transformers>=4.36.1
Requires-Dist: markdown2>=2.4.11
Requires-Dist: tiktoken>=0.5.2
